amqp/__init__.py
amqp/abstract_channel.py
amqp/basic_message.py
amqp/channel.py
amqp/connection.py
amqp/exceptions.py
amqp/method_framing.py
amqp/platform.py
amqp/protocol.py
amqp/sasl.py
amqp/serialization.py
amqp/spec.py
amqp/transport.py
amqp/utils.py
amqp-5.2.0.dist-info/LICENSE
amqp-5.2.0.dist-info/METADATA
amqp-5.2.0.dist-info/WHEEL
amqp-5.2.0.dist-info/top_level.txt
amqp-5.2.0.dist-info/RECORD
